mddc_cpp_helper.cpython-312-darwin.so
tests/test_mddc.py
tests/test_utils.py
tests/test_datasets.py
tests/__init__.py
tests/test_import.py
tests/test_find_optimal_coef.py
mddc-1.1.0.dist-info/RECORD
mddc-1.1.0.dist-info/WHEEL
mddc-1.1.0.dist-info/top_level.txt
mddc-1.1.0.dist-info/METADATA
mddc-1.1.0.dist-info/licenses/LICENSE
MDDC/__init__.py
MDDC/datasets/__init__.py
MDDC/datasets/_dataset.py
MDDC/datasets/data/statin101.csv
MDDC/datasets/data/statin49.csv
MDDC/datasets/data/sedative1000.csv
MDDC/datasets/data/betablocker500.csv
MDDC/datasets/data/statin49_with_cluster_idx.rst
MDDC/datasets/data/statin49_with_cluster_idx.csv
MDDC/datasets/data/betablocker500.rst
MDDC/datasets/data/sedative1000.rst
MDDC/datasets/data/statin49.rst
MDDC/datasets/data/statin101.rst
MDDC/utils/__init__.py
MDDC/utils/_utils.py
MDDC/MDDC/_mddc_boxplot.py
MDDC/MDDC/_mddc_monte_carlo.py
MDDC/MDDC/_helper.py
MDDC/MDDC/__init__.py
MDDC/MDDC/_find_optimal_coef.py
MDDC/MDDC/_mddc_basic.py
MDDC/MDDC/_mddc.py
