Metadata-Version: 2.4
Name: MDDC
Version: 1.1.0
Summary: Methods for detecting signals related to adverse event and medical product (e.g., drugs, vaccines) pairs. This includes a data generation function for simulating pharmacovigilance datasets, along with various utility functions. For more details, please see - Liu A, Mukhopadhyay R, Markatou M (2024). “MDDC: An R and Python Package for Adverse Event Identification in Pharmacovigilance Data.” arXiv preprint. https://doi.org/10.48550/arXiv.2410.01168.
Home-page: https://github.com/rmj3197/MDDC
Author: Raktim Mukhopadhyay, Anran Liu, Marianthi Markatou
Author-email: raktimmu@buffalo.edu, anranliu@buffalo.edu, markatou@buffalo.edu
Classifier: License :: OSI Approved :: GNU General Public License v3 (GPLv3)
Classifier: Programming Language :: Python :: 3
Classifier: Programming Language :: Python :: 3.10
Classifier: Programming Language :: Python :: 3.11
Classifier: Programming Language :: Python :: 3.12
Classifier: Programming Language :: Python :: 3.13
Classifier: Programming Language :: Python :: Implementation :: CPython
Requires-Python: >=3.10, <3.14
License-File: LICENSE
Requires-Dist: joblib>=1.2.0
Requires-Dist: matplotlib<3.9.0,>=3.7.1
Requires-Dist: numpy>=1.26.2
Requires-Dist: pandas>=2.1.3
Requires-Dist: peigen>=0.0.9
Requires-Dist: pybind11>=2.9.0
Requires-Dist: scipy>=1.11.0
Provides-Extra: test
Requires-Dist: pytest; extra == "test"
Dynamic: author
Dynamic: author-email
Dynamic: classifier
Dynamic: description
Dynamic: description-content-type
Dynamic: home-page
Dynamic: license-file
Dynamic: provides-extra
Dynamic: requires-dist
Dynamic: requires-python
Dynamic: summary
